{
    "classes": [
        {
            "className": "QrCodeItem",
            "lineNumber": 19,
            "object": true,
            "properties": [
                {
                    "constant": false,
                    "designable": true,
                    "final": false,
                    "index": 0,
                    "lineNumber": 22,
                    "name": "text",
                    "notify": "textChanged",
                    "override": false,
                    "read": "text",
                    "required": false,
                    "scriptable": true,
                    "stored": true,
                    "type": "QString",
                    "user": false,
                    "virtual": false,
                    "write": "setText"
                }
            ],
            "qualifiedClassName": "QrCodeItem",
            "signals": [
                {
                    "access": "public",
                    "index": 0,
                    "lineNumber": 33,
                    "name": "textChanged",
                    "returnType": "void"
                }
            ],
            "superClasses": [
                {
                    "access": "public",
                    "name": "QQuickPaintedItem"
                }
            ]
        }
    ],
    "inputFile": "QrCodeItem.h",
    "outputRevision": 69
}
